CONTRIBUTORS.txt
HISTORY.txt
LICENSE.txt
MANIFEST.in
README.txt
setup.py
src/inqbus/__init__.py
src/inqbus.ocf.agents.egg-info/PKG-INFO
src/inqbus.ocf.agents.egg-info/PKG-INFO~
src/inqbus.ocf.agents.egg-info/SOURCES.txt
src/inqbus.ocf.agents.egg-info/dependency_links.txt
src/inqbus.ocf.agents.egg-info/entry_points.txt
src/inqbus.ocf.agents.egg-info/namespace_packages.txt
src/inqbus.ocf.agents.egg-info/not-zip-safe
src/inqbus.ocf.agents.egg-info/requires.txt
src/inqbus.ocf.agents.egg-info/top_level.txt
src/inqbus/ocf/__init__.py
src/inqbus/ocf/agents/__init__.py
src/inqbus/ocf/agents/install_agents.py
src/inqbus/ocf/agents/openvpn.py
src/inqbus/ocf/agents/pidagent.py
src/inqbus/ocf/agents/pidbaseagent.py
src/inqbus/ocf/agents/test/__init__.py
src/inqbus/ocf/agents/test/data.py
src/inqbus/ocf/agents/test/dummy_daemon.py
src/inqbus/ocf/agents/test/test_openvpn.py
src/inqbus/ocf/agents/test/test_openvpn_fail.py
src/inqbus/ocf/agents/test/test_pidagent.py
src/inqbus/ocf/agents/test/test_pidbaseagent.py